{
  "db_name": "PostgreSQL",
  "query": "\n            SELECT table_name, column_name\n            FROM information_schema.columns\n            WHERE table_schema = 'public'\n            AND (\n                column_name ILIKE '%password%' OR\n                column_name ILIKE '%secret%' OR\n                column_name ILIKE '%token%' OR\n                column_name ILIKE '%key%'\n            )\n            AND data_type = 'text'\n            ",
  "describe": {
    "columns": [
      {
        "ordinal": 0,
        "name": "table_name",
        "type_info": "Name"
      },
      {
        "ordinal": 1,
        "name": "column_name",
        "type_info": "Name"
      }
    ],
    "parameters": {
      "Left": []
    },
    "nullable": [
      true,
      true
    ]
  },
  "hash": "fe72be97a20481310ceae3b70c92c64b85b4513097145d6790c40e139eac04d8"
}
