{
  "Romeo": [
    "Parlor",
    "Toilet B",
    "Parlor",
    "Toilet B",
    "Tank"
  ],
  "Christian": [
    "Toilet B",
    "Parlor",
    "Toilet B",
    "Tank",
    "Backyard"
  ],
  "Frank": [
    "Toilet A",
    "Tank",
    "Bin",
    "Toilet A",
    "Bin"
  ],
  "Emmanuel": [
    "Toilet B",
    "Parlor",
    "Toilet B",
    "Frontyard",
    "Toilet B"
  ],
  "Onel": [
    "Parlor",
    "Toilet A",
    "Parlor",
    "Bin",
    "Tank"
  ],
  "Usher": [
    "Frontyard",
    "Toilet B",
    "Tank",
    "Parlor",
    "Toilet B"
  ],
  "Ghislain": [
    "Toilet B",
    "Backyard",
    "Toilet B",
    "Parlor",
    "Toilet B"
  ],
  "Vitalis": [
    "Parlor",
    "Bin",
    "Parlor",
    "Toilet B",
    "Frontyard"
  ],
  "Nathan": [
    "Frontyard",
    "Parlor",
    "Frontyard",
    "Parlor",
    "Toilet A"
  ],
  "Mark": [
    "Parlor",
    "Toilet B",
    "Frontyard",
    "Toilet B",
    "Parlor"
  ],
  "Prosper": [
    "Tank",
    "Frontyard",
    "Backyard",
    "Toilet A",
    "Parlor"
  ],
  "Richmond": [
    "Bin",
    "Tank",
    "Frontyard",
    "Toilet B",
    "Parlor"
  ],
  "Desmond": [
    "Toilet B",
    "Parlor",
    "Toilet B",
    "Frontyard",
    "Parlor"
  ],
  "Maxwell": [
    "Tank",
    "Frontyard",
    "Parlor",
    "Frontyard",
    "Parlor"
  ],
  "Michael": [
    "Parlor",
    "Toilet B",
    "Tank",
    "Parlor",
    "Toilet B"
  ],
  "Derick": [
    "Backyard",
    "Frontyard",
    "Toilet A",
    "Parlor",
    "Toilet A"
  ],
  "Severian": [
    "Toilet A",
    "Parlor",
    "Toilet A",
    "Backyard",
    "Frontyard"
  ],
  "Junine": [
    "Frontyard",
    "Toilet A",
    "Parlor",
    "Tank",
    "Frontyard"
  ]
}